time_series_test.py
time_series_test-0.13.1.dist-info/COPYING
time_series_test-0.13.1.dist-info/WHEEL
time_series_test-0.13.1.dist-info/METADATA
time_series_test-0.13.1.dist-info/RECORD
