Metadata-Version: 2.3
Name: time_series_test
Version: 0.13.1
Summary: A statistical test and plotting function for time-series data in general, 
Keywords: signal processing,statistics,plotting,data analysis,crossvalidation
Author-email: Sebastiaan Mathôt <s.mathot@cogsci.nl>
Requires-Python: >=3.5
Requires-Dist: datamatrix
Requires-Dist: statsmodels
Requires-Dist: matplotlib
Project-URL: Documentation, https://github.com/smathot/time_series_test
Project-URL: Source, https://github.com/smathot/time_series_test
